elasticstore/__init__.py
elasticstore/lock.py
elasticstore/store.py
elasticstore/utils.py
elasticstore/legacy/__init__.py
elasticstore/legacy/store.py
elasticstore-2.5.dist-info/LICENSE
elasticstore-2.5.dist-info/METADATA
elasticstore-2.5.dist-info/WHEEL
elasticstore-2.5.dist-info/top_level.txt
elasticstore-2.5.dist-info/zip-safe
elasticstore-2.5.dist-info/RECORD
